toolsnetwork
