Metadata-Version: 1.0
Name: toolsnetwork
Version: 0.0.7
Summary: A very simple networking library for seperating MAC Frame written by Rohit G Bal (@rohitgbal).
Home-page: https://sites.google.com/site/rohitgbal/
Author: Rohit G BAl
Author-email: rohitgbal@gmail.com
License: MIT Lisence
Keywords: MAC,IPv4,IPv6
Platform: UNKNOWN
